nease/__init__.py
nease/functions.py
nease/load.py
nease/nease.py
nease/process.py
nease/data/database/ELM_interactions
nease/data/database/ELM_interactions_mouse
nease/data/database/Human
nease/data/database/Mouse
nease/data/database/elm
nease/data/database/elm_mouse
nease/data/database/non_coding.pkl
nease/data/database/pdb
nease/data/database/pdb_mouse
nease/data/network/PPI_Human.pkl
nease/data/network/PPI_mouse.pkl
nease/data/network/graph_human.pkl
nease/data/network/graph_mouse.pkl
nease/data/pathways/pathways_human
nease/data/pathways/pathways_mouse
nease-1.3.2.dist-info/licenses/LICENSE
nease-1.3.2.dist-info/METADATA
nease-1.3.2.dist-info/WHEEL
nease-1.3.2.dist-info/top_level.txt
nease-1.3.2.dist-info/RECORD
