Metadata-Version: 2.4
Name: nease
Version: 1.3.2
Summary: NEASE: A network-based approach for the enrichment of alternative splicing events
Home-page: https://github.com/louadi/NEASE
Author: Zakaria Louadi
Author-email: Zakaria.louadi@tum.de
License: GPLv3
Classifier: Programming Language :: Python :: 3
Classifier: Programming Language :: Python :: 3.7
Classifier: Programming Language :: Python :: 3.8
Classifier: License :: OSI Approved :: GNU General Public License v3 (GPLv3)
Classifier: Topic :: Scientific/Engineering :: Bio-Informatics
Requires-Python: >=3.6
License-File: LICENSE
Requires-Dist: pandas>=1.3.0
Requires-Dist: numpy>=1.19
Requires-Dist: networkx>=2.5
Requires-Dist: plotly>=4.14.3
Requires-Dist: scipy>=1.6.2
Requires-Dist: statsmodels>=0.12.2
Requires-Dist: gseapy>=0.10.7
Requires-Dist: matplotlib>=3.4.1
Requires-Dist: mygene>=3.2.2
Requires-Dist: kaleido
Dynamic: author
Dynamic: author-email
Dynamic: classifier
Dynamic: description
Dynamic: description-content-type
Dynamic: home-page
Dynamic: license
Dynamic: license-file
Dynamic: requires-dist
Dynamic: requires-python
Dynamic: summary
